LICENSE
MANIFEST.in
README.rst
setup.py
diesel/__init__.py
diesel/app.py
diesel/buffer.py
diesel/client.py
diesel/console.py
diesel/core.py
diesel/dnosetests.py
diesel/events.py
diesel/hub.py
diesel/interactive.py
diesel/logmod.py
diesel/pipeline.py
diesel/resolver.py
diesel/runtime.py
diesel/security.py
diesel/web.py
diesel.egg-info/PKG-INFO
diesel.egg-info/SOURCES.txt
diesel.egg-info/dependency_links.txt
diesel.egg-info/entry_points.txt
diesel.egg-info/requires.txt
diesel.egg-info/top_level.txt
diesel/protocols/DNS.py
diesel/protocols/__init__.py
diesel/protocols/dreadlock.py
diesel/protocols/irc.py
diesel/protocols/mongodb.py
diesel/protocols/nitro.py
diesel/protocols/pg.py
diesel/protocols/redis.py
diesel/protocols/riak.py
diesel/protocols/riak_palm.py
diesel/protocols/websockets.py
diesel/protocols/wsgi.py
diesel/protocols/zeromq.py
diesel/protocols/http/__init__.py
diesel/protocols/http/core.py
diesel/protocols/http/pool.py
diesel/util/__init__.py
diesel/util/debugtools.py
diesel/util/event.py
diesel/util/lock.py
diesel/util/pool.py
diesel/util/process.py
diesel/util/queue.py
diesel/util/stats.py
diesel/util/streams.py
diesel/util/patches/__init__.py
diesel/util/patches/requests_lib.py
examples/chat-redis.py
examples/chat.py
examples/child_test.py
examples/clocker.py
examples/combined.py
examples/combined_tls.py
examples/consolechat.py
examples/convoy.py
examples/crawler.py
examples/dhttpd
examples/dispatch.py
examples/dreadlocks.py
examples/echo.py
examples/event.py
examples/expygame.py
examples/fanout.py
examples/fire.py
examples/forker.py
examples/http.py
examples/http_client.py
examples/http_pool.py
examples/keep_alive.py
examples/newwait.py
examples/nitro.py
examples/nitro_echo_service.py
examples/queue.py
examples/queue_fairness_and_speed.py
examples/redis_lock.py
examples/redispub.py
examples/resolve_names.py
examples/santa.py
examples/signals.py
examples/sleep_server.py
examples/stdin.py
examples/stdin_stream.py
examples/synchronized.py
examples/test_dnosetest.py
examples/thread.py
examples/thread_pool.py
examples/timer.py
examples/timer_bench.py
examples/udp_echo.py
examples/web.py
examples/zeromq_echo_service.py
