Metadata-Version: 1.1
Name: diesel
Version: 3.0.24
Summary: Diesel is a coroutine-based networking library for Python
Home-page: http://diesel.io
Author: Jamie Turner/Boomplex LLC/Bump Technologies, Inc/Various Contributors
Author-email: jamie@bu.mp
License: UNKNOWN
Download-URL: https://github.com/dieseldev/diesel/archive/diesel-3.0.24.tar.gz
Platform: UNKNOWN
